fuzi/__init__.py
fuzi/version.py
fuzi/shell/__init__.py
fuzi/shell/usage.py
fuzi/src/temp.txt
fuzi-0.0.1.dist-info/LICENSE
fuzi-0.0.1.dist-info/METADATA
fuzi-0.0.1.dist-info/WHEEL
fuzi-0.0.1.dist-info/entry_points.txt
fuzi-0.0.1.dist-info/top_level.txt
fuzi-0.0.1.dist-info/zip-safe
fuzi-0.0.1.dist-info/RECORD
